huangjb_greenlet/__init__.py
huangjb_greenlet/_lib_build/greenlet/CObjects.cpp
huangjb_greenlet/_lib_build/greenlet/PyGreenlet.cpp
huangjb_greenlet/_lib_build/greenlet/PyGreenlet.hpp
huangjb_greenlet/_lib_build/greenlet/PyGreenletUnswitchable.cpp
huangjb_greenlet/_lib_build/greenlet/PyModule.cpp
huangjb_greenlet/_lib_build/greenlet/TBrokenGreenlet.cpp
huangjb_greenlet/_lib_build/greenlet/TExceptionState.cpp
huangjb_greenlet/_lib_build/greenlet/TGreenlet.cpp
huangjb_greenlet/_lib_build/greenlet/TGreenlet.hpp
huangjb_greenlet/_lib_build/greenlet/TGreenletGlobals.cpp
huangjb_greenlet/_lib_build/greenlet/TMainGreenlet.cpp
huangjb_greenlet/_lib_build/greenlet/TPythonState.cpp
huangjb_greenlet/_lib_build/greenlet/TStackState.cpp
huangjb_greenlet/_lib_build/greenlet/TThreadState.hpp
huangjb_greenlet/_lib_build/greenlet/TThreadStateCreator.hpp
huangjb_greenlet/_lib_build/greenlet/TThreadStateDestroy.cpp
huangjb_greenlet/_lib_build/greenlet/TUserGreenlet.cpp
huangjb_greenlet/_lib_build/greenlet/__init__.py
huangjb_greenlet/_lib_build/greenlet/__init__.pyc
huangjb_greenlet/_lib_build/greenlet/_greenlet.cpython-313t-arm-linux-gnueabihf.so
huangjb_greenlet/_lib_build/greenlet/greenlet.cpp
huangjb_greenlet/_lib_build/greenlet/greenlet.h
huangjb_greenlet/_lib_build/greenlet/greenlet_allocator.hpp
huangjb_greenlet/_lib_build/greenlet/greenlet_compiler_compat.hpp
huangjb_greenlet/_lib_build/greenlet/greenlet_cpython_compat.hpp
huangjb_greenlet/_lib_build/greenlet/greenlet_exceptions.hpp
huangjb_greenlet/_lib_build/greenlet/greenlet_internal.hpp
huangjb_greenlet/_lib_build/greenlet/greenlet_msvc_compat.hpp
huangjb_greenlet/_lib_build/greenlet/greenlet_refs.hpp
huangjb_greenlet/_lib_build/greenlet/greenlet_slp_switch.hpp
huangjb_greenlet/_lib_build/greenlet/greenlet_thread_support.hpp
huangjb_greenlet/_lib_build/greenlet/slp_platformselect.h
huangjb_greenlet/_lib_build/greenlet/__pycache__/__init__.cpython-313.pyc
huangjb_greenlet/_lib_build/greenlet/platform/__init__.py
huangjb_greenlet-3.2.3.dist-info/METADATA
huangjb_greenlet-3.2.3.dist-info/WHEEL
huangjb_greenlet-3.2.3.dist-info/top_level.txt
huangjb_greenlet-3.2.3.dist-info/RECORD
