Metadata-Version: 2.4
Name: huangjb_greenlet
Version: 3.2.3
Summary: Custom build of greenlet for linux_armv7l
Home-page: https://github.com/wecon/custom_packages
Author: Wecon
Author-email: support@wecon.com
Platform: linux_armv7l
Classifier: Programming Language :: Python :: 3
Classifier: License :: OSI Approved :: BSD License
Classifier: Operating System :: POSIX :: Linux
Requires-Python: >=3.8
Dynamic: author
Dynamic: author-email
Dynamic: classifier
Dynamic: home-page
Dynamic: platform
Dynamic: requires-python
Dynamic: summary
